keble_pytest_helpers/__init__.py
keble_pytest_helpers/embeddings/__init__.py
keble_pytest_helpers/embeddings/mock_embeddings.py
keble_pytest_helpers/embeddings/mock_embeddings_model.py
keble_pytest_helpers/llm/__init__.py
keble_pytest_helpers/llm/mock_base_chat_model.py
keble_pytest_helpers/llm/mock_llm.py
keble_pytest_helpers/utils.py
keble_pytest_helpers-0.0.5.dist-info/METADATA
keble_pytest_helpers-0.0.5.dist-info/WHEEL
keble_pytest_helpers-0.0.5.dist-info/RECORD
