Metadata-Version: 2.1
Name: keble-pytest-helpers
Version: 0.0.5
Summary: 
Author: zhenhao-ma
Author-email: bob0103779@gmail.com
Requires-Python: >=3.10,<4.0
Classifier: Programming Language :: Python :: 3
Classifier: Programming Language :: Python :: 3.10
Classifier: Programming Language :: Python :: 3.11
Classifier: Programming Language :: Python :: 3.12
Requires-Dist: jsonlines (>=4,<5)
Requires-Dist: keble-helpers (>=0,<1)
Requires-Dist: langchain (>=0.1.12,<0.2.0)
Requires-Dist: langchain-community (>=0.0.28,<0.0.29)
Requires-Dist: langchain-openai (>=0.0.2.post1,<0.0.3)
Requires-Dist: pytest (>=8,<9)
Requires-Dist: pytest-asyncio (>=0,<1)
